{
    "ret": true,
    "data": {
        "sightName": "馬祖酒廠",
        "mapUrl":"https://www.google.com/maps/embed?pb=!1m18!1m12!1m3!1d3581.098305958512!2d119.94964981469407!3d26.16092769834611!2m3!1f0!2f0!3f0!3m2!1i1024!2i768!4f13.1!3m3!1m2!1s0x3441708ad3170f8f%3A0xf60a8ff8ac4331ba!2z6aas56WW6YWS5bug5a-m5qWt6IKh5Lu95pyJ6ZmQ5YWs5Y-4!5e0!3m2!1szh-TW!2stw!4v1580446827869!5m2!1szh-TW!2stw",
        "bannerImg": "https://img3.okgo.tw/titlepic/b926_1.jpg",
        "galleryImgs": ["https://img3.okgo.tw/titlepic/b926_1.jpg","https://img3.okgo.tw/titlepic/b926_2.jpg","https://img3.okgo.tw/titlepic/b926_4.jpg","https://img3.okgo.tw/titlepic/b926_8.jpg"],
        "detailDesc": "馬祖酒廠位於南竿鄉復興村牛背嶺，成立於民國45（1956）年，各種名酒皆源自附近之天然甘泉釀酒，而陳年老酒必須存放至陰冷的山洞坑道中兩年以上才能銷售。馬祖的美酒遠近馳名，其中大麴酒、高梁酒及陳年老酒最受青睞，另外還有馬祖高粱、馬祖陳高、東引陳高（已改名東湧陳高）、馬祖大麴、陳年大麴、雲台古酒。廠內更貼心的服務還有設置展示室及播放多媒體簡報，讓遊客們能更進一步的認識「馬祖酒廠」。",
        "itemClaim": "[轉載於玩全台灣]"
    }
  }
  